frostaura/__init__.py
frostaura/data_access/__init__.py
frostaura/data_access/modalities_data_access.py
frostaura/data_access/modalities_data_access__telegram.py
frostaura/engines/__init__.py
frostaura/engines/asset_calculations_engine__simple.py
frostaura/engines/subordinate_function.py
frostaura/managers/__init__.py
frostaura/managers/zeus_manager.py
frostaura/managers/zeus_manager__telegram.py
frostaura/models/__init__.py
frostaura/models/profit_calculation_result.py
frostaura/models/symbol_data.py
frostaura/models/valuation_result.py
frostaura/models/visualization_types.py
frostaura/resources/easy_equities_us_exclusions.json
frostaura/resources/easy_equities_us_stocks.json
frostaura.intelligence.zeus-0.0.2.dist-info/METADATA
frostaura.intelligence.zeus-0.0.2.dist-info/WHEEL
frostaura.intelligence.zeus-0.0.2.dist-info/top_level.txt
frostaura.intelligence.zeus-0.0.2.dist-info/RECORD
